{
  "SM-P": {
    "name": "SM-P 太陽&月亮 特典卡",
    "cards": {
      "001/SM-P": {
        "name": "皮卡丘",
        "rarity": "PROMO",
        "image": ""
      },
      "002/SM-P": {
        "name": "謎擬Ｑ",
        "rarity": "PROMO",
        "image": ""
      },
      "003/SM-P": {
        "name": "伊布",
        "rarity": "PROMO",
        "image": ""
      },
      "004/SM-P": {
        "name": "甜冷美后",
        "rarity": "PROMO",
        "image": ""
      },
      "005/SM-P": {
        "name": "鳳王GX",
        "rarity": "PROMO",
        "image": ""
      },
      "006/SM-P": {
        "name": "鍬農炮蟲",
        "rarity": "PROMO",
        "image": ""
      },
      "007/SM-P": {
        "name": "卡璞・鳴鳴GX",
        "rarity": "PROMO",
        "image": ""
      },
      "008/SM-P": {
        "name": "破破舵輪",
        "rarity": "PROMO",
        "image": ""
      },
      "009/SM-P": {
        "name": "瑪夏多",
        "rarity": "PROMO",
        "image": ""
      },
      "010/SM-P": {
        "name": "爆肌蚊GX",
        "rarity": "PROMO",
        "image": ""
      },
      "011/SM-P": {
        "name": "三首惡龍",
        "rarity": "PROMO",
        "image": ""
      },
      "012/SM-P": {
        "name": "仙子伊布GX",
        "rarity": "PROMO",
        "image": ""
      },
      "013/SM-P": {
        "name": "智揮猩",
        "rarity": "PROMO",
        "image": ""
      },
      "014/SM-P": {
        "name": "巢穴球",
        "rarity": "PROMO",
        "image": ""
      },
      "015/SM-P": {
        "name": "高級球",
        "rarity": "PROMO",
        "image": ""
      },
      "016/SM-P": {
        "name": "神奇糖果",
        "rarity": "PROMO",
        "image": ""
      },
      "017/SM-P": {
        "name": "寶可夢交替",
        "rarity": "PROMO",
        "image": ""
      },
      "018/SM-P": {
        "name": "講究頭帶",
        "rarity": "PROMO",
        "image": ""
      },
      "019/SM-P": {
        "name": "祈願接力棒",
        "rarity": "PROMO",
        "image": ""
      },
      "020/SM-P": {
        "name": "哈烏",
        "rarity": "PROMO",
        "image": ""
      },
      "021/SM-P": {
        "name": "莉莉艾",
        "rarity": "PROMO",
        "image": ""
      },
      "022/SM-P": {
        "name": "葉伊布GX",
        "rarity": "PROMO",
        "image": ""
      },
      "023/SM-P": {
        "name": "呆呆獸",
        "rarity": "PROMO",
        "image": ""
      },
      "024/SM-P": {
        "name": "水君",
        "rarity": "PROMO",
        "image": ""
      },
      "025/SM-P": {
        "name": "蓋歐卡",
        "rarity": "PROMO",
        "image": ""
      },
      "026/SM-P": {
        "name": "冰伊布GX",
        "rarity": "PROMO",
        "image": ""
      },
      "027/SM-P": {
        "name": "雷電獸",
        "rarity": "PROMO",
        "image": ""
      },
      "028/SM-P": {
        "name": "騎拉帝納",
        "rarity": "PROMO",
        "image": ""
      },
      "029/SM-P": {
        "name": "烏賊王",
        "rarity": "PROMO",
        "image": ""
      },
      "030/SM-P": {
        "name": "奈克洛茲瑪 拂曉之翼GX",
        "rarity": "PROMO",
        "image": ""
      },
      "031/SM-P": {
        "name": "瑪狃拉",
        "rarity": "PROMO",
        "image": ""
      },
      "032/SM-P": {
        "name": "阿羅拉 地鼠",
        "rarity": "PROMO",
        "image": ""
      },
      "033/SM-P": {
        "name": "卡璞・蝶蝶",
        "rarity": "PROMO",
        "image": ""
      },
      "034/SM-P": {
        "name": "七夕青鳥",
        "rarity": "PROMO",
        "image": ""
      },
      "035/SM-P": {
        "name": "究極奈克洛茲瑪GX",
        "rarity": "PROMO",
        "image": ""
      },
      "036/SM-P": {
        "name": "捕網球",
        "rarity": "PROMO",
        "image": ""
      },
      "037/SM-P": {
        "name": "神祕珍寶",
        "rarity": "PROMO",
        "image": ""
      },
      "038/SM-P": {
        "name": "觀光客",
        "rarity": "PROMO",
        "image": ""
      },
      "039/SM-P": {
        "name": "竹蘭",
        "rarity": "PROMO",
        "image": ""
      },
      "040/SM-P": {
        "name": "電次",
        "rarity": "PROMO",
        "image": ""
      },
      "041/SM-P": {
        "name": "究極空間",
        "rarity": "PROMO",
        "image": ""
      },
      "042/SM-P": {
        "name": "基拉祈",
        "rarity": "PROMO",
        "image": ""
      },
      "043/SM-P": {
        "name": "時拉比&妙蛙花GX",
        "rarity": "PROMO",
        "image": ""
      },
      "044/SM-P": {
        "name": "噴火龍",
        "rarity": "PROMO",
        "image": ""
      },
      "045/SM-P": {
        "name": "水晶燈火靈",
        "rarity": "PROMO",
        "image": ""
      },
      "046/SM-P": {
        "name": "波爾凱尼恩",
        "rarity": "PROMO",
        "image": ""
      },
      "047/SM-P": {
        "name": "水箭龜GX",
        "rarity": "PROMO",
        "image": ""
      },
      "048/SM-P": {
        "name": "尼多后",
        "rarity": "PROMO",
        "image": ""
      },
      "049/SM-P": {
        "name": "超夢",
        "rarity": "PROMO",
        "image": ""
      },
      "050/SM-P": {
        "name": "瑪夏多",
        "rarity": "PROMO",
        "image": ""
      },
      "051/SM-P": {
        "name": "瑪夏多&怪力GX",
        "rarity": "PROMO",
        "image": ""
      },
      "052/SM-P": {
        "name": "壘磊石",
        "rarity": "PROMO",
        "image": ""
      },
      "053/SM-P": {
        "name": "伊布&卡比獸GX",
        "rarity": "PROMO",
        "image": ""
      },
      "054/SM-P": {
        "name": "貓老大",
        "rarity": "PROMO",
        "image": ""
      },
      "055/SM-P": {
        "name": "聯手切換",
        "rarity": "PROMO",
        "image": ""
      },
      "056/SM-P": {
        "name": "火之結晶",
        "rarity": "PROMO",
        "image": ""
      },
      "057/SM-P": {
        "name": "隱密風帽",
        "rarity": "PROMO",
        "image": ""
      },
      "058/SM-P": {
        "name": "肌力護膝",
        "rarity": "PROMO",
        "image": ""
      },
      "059/SM-P": {
        "name": "阿杏",
        "rarity": "PROMO",
        "image": ""
      },
      "060/SM-P": {
        "name": "教練訓練家",
        "rarity": "PROMO",
        "image": ""
      },
      "061/SM-P": {
        "name": "碧藍的探索",
        "rarity": "PROMO",
        "image": ""
      },
      "062/SM-P": {
        "name": "常青森林",
        "rarity": "PROMO",
        "image": ""
      },
      "064/SM-P": {
        "name": "噴火龍GX",
        "rarity": "PROMO",
        "image": "https://asia.pokemon-card.com/tw/card-img/tw00008112.png"
      },
      "066/SM-P": {
        "name": "水箭龜&波加曼GX",
        "rarity": "PROMO",
        "image": ""
      },
      "073/SM-P": {
        "name": "快龍GX",
        "rarity": "PROMO",
        "image": ""
      },
      "074/SM-P": {
        "name": "超級長耳兔&胖丁GX",
        "rarity": "PROMO",
        "image": ""
      },
      "083/SM-P": {
        "name": "基本草能量",
        "rarity": "PROMO",
        "image": ""
      },
      "084/SM-P": {
        "name": "基本火能量",
        "rarity": "PROMO",
        "image": ""
      },
      "085/SM-P": {
        "name": "基本水能量",
        "rarity": "PROMO",
        "image": ""
      },
      "086/SM-P": {
        "name": "基本雷能量",
        "rarity": "PROMO",
        "image": ""
      },
      "087/SM-P": {
        "name": "基本超能量",
        "rarity": "PROMO",
        "image": ""
      },
      "088/SM-P": {
        "name": "基本鬥能量",
        "rarity": "PROMO",
        "image": ""
      },
      "089/SM-P": {
        "name": "基本惡能量",
        "rarity": "PROMO",
        "image": ""
      },
      "090/SM-P": {
        "name": "基本鋼能量",
        "rarity": "PROMO",
        "image": ""
      },
      "091/SM-P": {
        "name": "基本妖能量",
        "rarity": "PROMO",
        "image": ""
      },
      "092/SM-P": {
        "name": "咚咚鼠GX",
        "rarity": "PROMO",
        "image": ""
      },
      "093/SM-P": {
        "name": "卡璞・蝶蝶GX",
        "rarity": "PROMO",
        "image": ""
      },
      "094/SM-P": {
        "name": "伊布GX",
        "rarity": "PROMO",
        "image": ""
      }
    },
    "releaseDate": "2019-10-9"
  }
}