{
  "SVAM": {
    "name": "起始組合ex 新葉喵&路卡利歐ex",
    "releaseDate": "2023-02-03",
    "cards": {
      "001/023": {
        "name": "蘑蘑菇",
        "rarity": "",
        "image": "https://asia.pokemon-card.com/tw/card-img/tw00007750.png"
      },
      "002/023": {
        "name": "斗笠菇",
        "rarity": "",
        "image": "https://asia.pokemon-card.com/tw/card-img/tw00007751.png"
      },
      "003/023": {
        "name": "熱帶龍",
        "rarity": "",
        "image": "https://asia.pokemon-card.com/tw/card-img/tw00007752.png"
      },
      "004/023": {
        "name": "新葉喵",
        "rarity": "",
        "image": "https://asia.pokemon-card.com/tw/card-img/tw00007753.png"
      },
      "005/023": {
        "name": "蒂蕾喵",
        "rarity": "",
        "image": "https://asia.pokemon-card.com/tw/card-img/tw00007754.png"
      },
      "006/023": {
        "name": "魔幻假面喵",
        "rarity": "",
        "image": "https://asia.pokemon-card.com/tw/card-img/tw00007755.png"
      },
      "007/023": {
        "name": "團珠蛛",
        "rarity": "",
        "image": "https://asia.pokemon-card.com/tw/card-img/tw00007756.png"
      },
      "008/023": {
        "name": "利歐路",
        "rarity": "",
        "image": "https://asia.pokemon-card.com/tw/card-img/tw00007757.png"
      },
      "009/023": {
        "name": "路卡利歐ex",
        "rarity": "",
        "image": "https://asia.pokemon-card.com/tw/card-img/tw00007758.png"
      },
      "010/023": {
        "name": "巨石丁",
        "rarity": "",
        "image": "https://asia.pokemon-card.com/tw/card-img/tw00007759.png"
      },
      "011/023": {
        "name": "愛吃豚",
        "rarity": "",
        "image": "https://asia.pokemon-card.com/tw/card-img/tw00007760.png"
      },
      "012/023": {
        "name": "能量轉移",
        "rarity": "",
        "image": "https://asia.pokemon-card.com/tw/card-img/tw00007761.png"
      },
      "013/023": {
        "name": "能量輸送",
        "rarity": "",
        "image": "https://asia.pokemon-card.com/tw/card-img/tw00007762.png"
      },
      "014/023": {
        "name": "傷藥",
        "rarity": "",
        "image": "https://asia.pokemon-card.com/tw/card-img/tw00007763.png"
      },
      "015/023": {
        "name": "巢穴球",
        "rarity": "",
        "image": "https://asia.pokemon-card.com/tw/card-img/tw00007764.png"
      },
      "016/023": {
        "name": "高級球",
        "rarity": "",
        "image": "https://asia.pokemon-card.com/tw/card-img/tw00007765.png"
      },
      "017/023": {
        "name": "寶可裝置3.0",
        "rarity": "",
        "image": "https://asia.pokemon-card.com/tw/card-img/tw00007766.png"
      },
      "018/023": {
        "name": "寶可夢交替",
        "rarity": "",
        "image": "https://asia.pokemon-card.com/tw/card-img/tw00007767.png"
      },
      "019/023": {
        "name": "寶可夢捕捉器",
        "rarity": "",
        "image": "https://asia.pokemon-card.com/tw/card-img/tw00007768.png"
      },
      "020/023": {
        "name": "裁判",
        "rarity": "",
        "image": "https://asia.pokemon-card.com/tw/card-img/tw00007769.png"
      },
      "021/023": {
        "name": "短褲小子",
        "rarity": "",
        "image": "https://asia.pokemon-card.com/tw/card-img/tw00007770.png"
      },
      "022/023": {
        "name": "妮莫",
        "rarity": "",
        "image": "https://asia.pokemon-card.com/tw/card-img/tw00007771.png"
      },
      "023/023": {
        "name": "博士的研究 奧琳博士",
        "rarity": "",
        "image": "https://asia.pokemon-card.com/tw/card-img/tw00007772.png"
      }
    }
  }
}