{
  "M3": {
    "name": "虛無歸零",
    "releaseDate": "2026-02-06",
    "cards": {
      "001/080": {
        "name": "圓絲蛛",
        "rarity": "C",
        "image": ""
      },
      "002/080": {
        "name": "阿利多斯",
        "rarity": "C",
        "image": ""
      },
      "003/080": {
        "name": "謝米",
        "rarity": "U",
        "image": ""
      },
      "004/080": {
        "name": "藤藤蛇",
        "rarity": "C",
        "image": ""
      },
      "005/080": {
        "name": "青藤蛇",
        "rarity": "C",
        "image": ""
      },
      "006/080": {
        "name": "君主蛇",
        "rarity": "R",
        "image": ""
      },
      "007/080": {
        "name": "粉蝶蟲",
        "rarity": "C",
        "image": ""
      },
      "008/080": {
        "name": "粉蝶蛹",
        "rarity": "C",
        "image": ""
      },
      "009/080": {
        "name": "彩粉蝶",
        "rarity": "U",
        "image": ""
      },
      "010/080": {
        "name": "木木梟",
        "rarity": "C",
        "image": ""
      },
      "011/080": {
        "name": "投羽梟",
        "rarity": "C",
        "image": ""
      },
      "012/080": {
        "name": "狙射樹梟ex",
        "rarity": "RR",
        "image": ""
      },
      "013/080": {
        "name": "火箭雀",
        "rarity": "C",
        "image": ""
      },
      "014/080": {
        "name": "烈箭鷹",
        "rarity": "U",
        "image": ""
      },
      "015/080": {
        "name": "夜盜火蜥",
        "rarity": "C",
        "image": ""
      },
      "016/080": {
        "name": "焰后蜥ex",
        "rarity": "RR",
        "image": ""
      },
      "017/080": {
        "name": "爆焰龜獸",
        "rarity": "U",
        "image": ""
      },
      "018/080": {
        "name": "小海獅",
        "rarity": "C",
        "image": ""
      },
      "019/080": {
        "name": "白海獅",
        "rarity": "R",
        "image": ""
      },
      "020/080": {
        "name": "海星星",
        "rarity": "C",
        "image": ""
      },
      "021/080": {
        "name": "超級寶石海星ex",
        "rarity": "RR",
        "image": ""
      },
      "022/080": {
        "name": "冰雪龍",
        "rarity": "C",
        "image": ""
      },
      "023/080": {
        "name": "冰雪巨龍",
        "rarity": "U",
        "image": ""
      },
      "024/080": {
        "name": "波爾凱尼恩",
        "rarity": "U",
        "image": ""
      },
      "025/080": {
        "name": "小貓怪",
        "rarity": "C",
        "image": ""
      },
      "026/080": {
        "name": "勒克貓",
        "rarity": "U",
        "image": ""
      },
      "027/080": {
        "name": "倫琴貓",
        "rarity": "R",
        "image": ""
      },
      "028/080": {
        "name": "咚咚鼠",
        "rarity": "C",
        "image": ""
      },
      "029/080": {
        "name": "皮皮",
        "rarity": "C",
        "image": ""
      },
      "030/080": {
        "name": "超級皮可西ex",
        "rarity": "RR",
        "image": ""
      },
      "031/080": {
        "name": "大嘴娃",
        "rarity": "C",
        "image": ""
      },
      "032/080": {
        "name": "妙喵",
        "rarity": "C",
        "image": ""
      },
      "033/080": {
        "name": "超能妙喵",
        "rarity": "U",
        "image": ""
      },
      "034/080": {
        "name": "粉香香",
        "rarity": "C",
        "image": ""
      },
      "035/080": {
        "name": "芳香精",
        "rarity": "U",
        "image": ""
      },
      "036/080": {
        "name": "朝北鼻",
        "rarity": "C",
        "image": ""
      },
      "037/080": {
        "name": "大朝北鼻",
        "rarity": "C",
        "image": ""
      },
      "038/080": {
        "name": "沙河馬",
        "rarity": "C",
        "image": ""
      },
      "039/080": {
        "name": "河馬獸",
        "rarity": "U",
        "image": ""
      },
      "040/080": {
        "name": "土地雲",
        "rarity": "R",
        "image": ""
      },
      "041/080": {
        "name": "龜腳腳",
        "rarity": "C",
        "image": ""
      },
      "042/080": {
        "name": "龜足巨鎧",
        "rarity": "U",
        "image": ""
      },
      "043/080": {
        "name": "寶寶暴龍",
        "rarity": "C",
        "image": ""
      },
      "044/080": {
        "name": "怪顎龍",
        "rarity": "U",
        "image": ""
      },
      "045/080": {
        "name": "摔角鷹人",
        "rarity": "C",
        "image": ""
      },
      "046/080": {
        "name": "超級基格爾德ex",
        "rarity": "RR",
        "image": ""
      },
      "047/080": {
        "name": "鬼斯",
        "rarity": "C",
        "image": ""
      },
      "048/080": {
        "name": "鬼斯通",
        "rarity": "C",
        "image": ""
      },
      "049/080": {
        "name": "耿鬼",
        "rarity": "U",
        "image": ""
      },
      "050/080": {
        "name": "鉗尾蠍",
        "rarity": "C",
        "image": ""
      },
      "051/080": {
        "name": "龍王蠍",
        "rarity": "U",
        "image": ""
      },
      "052/080": {
        "name": "伊裴爾塔爾ex",
        "rarity": "RR",
        "image": ""
      },
      "053/080": {
        "name": "古劍豹",
        "rarity": "R",
        "image": ""
      },
      "054/080": {
        "name": "超級盔甲鳥ex",
        "rarity": "RR",
        "image": ""
      },
      "055/080": {
        "name": "獨劍鞘",
        "rarity": "C",
        "image": ""
      },
      "056/080": {
        "name": "雙劍鞘",
        "rarity": "C",
        "image": ""
      },
      "057/080": {
        "name": "堅盾劍怪",
        "rarity": "U",
        "image": ""
      },
      "058/080": {
        "name": "鑰圈兒",
        "rarity": "C",
        "image": ""
      },
      "059/080": {
        "name": "小拉達",
        "rarity": "C",
        "image": ""
      },
      "060/080": {
        "name": "拉達",
        "rarity": "U",
        "image": ""
      },
      "061/080": {
        "name": "喵喵ex",
        "rarity": "RR",
        "image": ""
      },
      "062/080": {
        "name": "卡比獸",
        "rarity": "C",
        "image": ""
      },
      "063/080": {
        "name": "掘掘兔",
        "rarity": "C",
        "image": ""
      },
      "064/080": {
        "name": "掘地兔",
        "rarity": "U",
        "image": ""
      },
      "065/080": {
        "name": "小箭雀",
        "rarity": "C",
        "image": ""
      },
      "066/080": {
        "name": "多麗米亞",
        "rarity": "C",
        "image": ""
      },
      "067/080": {
        "name": "能量撢子",
        "rarity": "U",
        "image": ""
      },
      "068/080": {
        "name": "陳舊的顎之化石",
        "rarity": "C",
        "image": ""
      },
      "069/080": {
        "name": "陳舊的鰭之化石",
        "rarity": "C",
        "image": ""
      },
      "070/080": {
        "name": "寶可平板",
        "rarity": "U",
        "image": ""
      },
      "071/080": {
        "name": "密阿雷格雷派餅",
        "rarity": "U",
        "image": ""
      },
      "072/080": {
        "name": "核心記憶碟",
        "rarity": "U",
        "image": ""
      },
      "073/080": {
        "name": "塔拉剛",
        "rarity": "U",
        "image": ""
      },
      "074/080": {
        "name": "琵魯",
        "rarity": "U",
        "image": ""
      },
      "075/080": {
        "name": "鳴依的勉勵",
        "rarity": "U",
        "image": ""
      },
      "076/080": {
        "name": "由紫",
        "rarity": "U",
        "image": ""
      },
      "077/080": {
        "name": "密阿雷市",
        "rarity": "U",
        "image": ""
      },
      "078/080": {
        "name": "增強草能量",
        "rarity": "R",
        "image": ""
      },
      "079/080": {
        "name": "感應超能量",
        "rarity": "R",
        "image": ""
      },
      "080/080": {
        "name": "硬岩鬥能量",
        "rarity": "R",
        "image": ""
      }
    }
  }
}