{
  "SC1D": {
    "name": "V起始牌組 劍&盾",
    "cards": {
      "001/164": {
        "name": "飛天螳螂",
        "rarity": "—",
        "image": "https://asia.pokemon-card.com/tw/card-img/tw00002576.png"
      },
      "002/164": {
        "name": "時拉比V",
        "rarity": "—",
        "image": "https://asia.pokemon-card.com/tw/card-img/tw00002577.png"
      },
      "003/164": {
        "name": "毒薔薇",
        "rarity": "—",
        "image": "https://asia.pokemon-card.com/tw/card-img/tw00002578.png"
      },
      "004/164": {
        "name": "雪笠怪",
        "rarity": "—",
        "image": "https://asia.pokemon-card.com/tw/card-img/tw00002579.png"
      },
      "005/164": {
        "name": "暴雪王",
        "rarity": "—",
        "image": "https://asia.pokemon-card.com/tw/card-img/tw00002580.png"
      },
      "006/164": {
        "name": "木棉球",
        "rarity": "—",
        "image": "https://asia.pokemon-card.com/tw/card-img/tw00002581.png"
      },
      "007/164": {
        "name": "風妖精",
        "rarity": "—",
        "image": "https://asia.pokemon-card.com/tw/card-img/tw00002582.png"
      },
      "008/164": {
        "name": "沙鈴仙人掌",
        "rarity": "—",
        "image": "https://asia.pokemon-card.com/tw/card-img/tw00002583.png"
      },
      "009/164": {
        "name": "鐵蟻",
        "rarity": "—",
        "image": "https://asia.pokemon-card.com/tw/card-img/tw00002584.png"
      },
      "010/164": {
        "name": "敲音猴",
        "rarity": "—",
        "image": "https://asia.pokemon-card.com/tw/card-img/tw00002585.png"
      },
      "011/164": {
        "name": "啪咚猴",
        "rarity": "—",
        "image": "https://asia.pokemon-card.com/tw/card-img/tw00002586.png"
      },
      "012/164": {
        "name": "轟擂金剛猩",
        "rarity": "—",
        "image": "https://asia.pokemon-card.com/tw/card-img/tw00002587.png"
      },
      "013/164": {
        "name": "轟擂金剛猩V",
        "rarity": "—",
        "image": "https://asia.pokemon-card.com/tw/card-img/tw00002588.png"
      },
      "014/164": {
        "name": "索偵蟲",
        "rarity": "—",
        "image": "https://asia.pokemon-card.com/tw/card-img/tw00002589.png"
      },
      "015/164": {
        "name": "啃果蟲",
        "rarity": "—",
        "image": "https://asia.pokemon-card.com/tw/card-img/tw00002590.png"
      },
      "016/164": {
        "name": "豐蜜龍",
        "rarity": "—",
        "image": "https://asia.pokemon-card.com/tw/card-img/tw00002591.png"
      },
      "017/164": {
        "name": "六尾",
        "rarity": "—",
        "image": "https://asia.pokemon-card.com/tw/card-img/tw00002592.png"
      },
      "018/164": {
        "name": "九尾",
        "rarity": "—",
        "image": "https://asia.pokemon-card.com/tw/card-img/tw00002593.png"
      },
      "019/164": {
        "name": "鴨嘴火獸",
        "rarity": "—",
        "image": "https://asia.pokemon-card.com/tw/card-img/tw00002594.png"
      },
      "020/164": {
        "name": "鴨嘴炎獸",
        "rarity": "—",
        "image": "https://asia.pokemon-card.com/tw/card-img/tw00002595.png"
      },
      "021/164": {
        "name": "比克提尼V",
        "rarity": "—",
        "image": "https://asia.pokemon-card.com/tw/card-img/tw00002596.png"
      },
      "022/164": {
        "name": "熔蟻獸",
        "rarity": "—",
        "image": "https://asia.pokemon-card.com/tw/card-img/tw00002597.png"
      },
      "023/164": {
        "name": "爆焰龜獸",
        "rarity": "—",
        "image": "https://asia.pokemon-card.com/tw/card-img/tw00002598.png"
      },
      "024/164": {
        "name": "炎兔兒",
        "rarity": "—",
        "image": "https://asia.pokemon-card.com/tw/card-img/tw00002599.png"
      },
      "025/164": {
        "name": "騰蹴小將",
        "rarity": "—",
        "image": "https://asia.pokemon-card.com/tw/card-img/tw00002600.png"
      },
      "026/164": {
        "name": "閃焰王牌",
        "rarity": "—",
        "image": "https://asia.pokemon-card.com/tw/card-img/tw00002601.png"
      },
      "027/164": {
        "name": "閃焰王牌V",
        "rarity": "—",
        "image": "https://asia.pokemon-card.com/tw/card-img/tw00002602.png"
      },
      "028/164": {
        "name": "燒火蚣",
        "rarity": "—",
        "image": "https://asia.pokemon-card.com/tw/card-img/tw00002603.png"
      },
      "029/164": {
        "name": "燒火蚣",
        "rarity": "—",
        "image": "https://asia.pokemon-card.com/tw/card-img/tw00002604.png"
      },
      "030/164": {
        "name": "焚焰蚣",
        "rarity": "—",
        "image": "https://asia.pokemon-card.com/tw/card-img/tw00002605.png"
      },
      "031/164": {
        "name": "大舌貝",
        "rarity": "—",
        "image": "https://asia.pokemon-card.com/tw/card-img/tw00002606.png"
      },
      "032/164": {
        "name": "刺甲貝",
        "rarity": "—",
        "image": "https://asia.pokemon-card.com/tw/card-img/tw00002607.png"
      },
      "033/164": {
        "name": "大鉗蟹",
        "rarity": "—",
        "image": "https://asia.pokemon-card.com/tw/card-img/tw00002608.png"
      },
      "034/164": {
        "name": "角金魚",
        "rarity": "—",
        "image": "https://asia.pokemon-card.com/tw/card-img/tw00002609.png"
      },
      "035/164": {
        "name": "拉普拉斯",
        "rarity": "—",
        "image": "https://asia.pokemon-card.com/tw/card-img/tw00002610.png"
      },
      "036/164": {
        "name": "拉普拉斯V",
        "rarity": "—",
        "image": "https://asia.pokemon-card.com/tw/card-img/tw00002611.png"
      },
      "037/164": {
        "name": "巨翅飛魚",
        "rarity": "—",
        "image": "https://asia.pokemon-card.com/tw/card-img/tw00002612.png"
      },
      "038/164": {
        "name": "淚眼蜥",
        "rarity": "—",
        "image": "https://asia.pokemon-card.com/tw/card-img/tw00002613.png"
      },
      "039/164": {
        "name": "變澀蜥",
        "rarity": "—",
        "image": "https://asia.pokemon-card.com/tw/card-img/tw00002614.png"
      },
      "040/164": {
        "name": "千面避役",
        "rarity": "—",
        "image": "https://asia.pokemon-card.com/tw/card-img/tw00002615.png"
      },
      "041/164": {
        "name": "千面避役V",
        "rarity": "—",
        "image": "https://asia.pokemon-card.com/tw/card-img/tw00002616.png"
      },
      "042/164": {
        "name": "咬咬龜",
        "rarity": "—",
        "image": "https://asia.pokemon-card.com/tw/card-img/tw00002617.png"
      },
      "043/164": {
        "name": "暴噬龜",
        "rarity": "—",
        "image": "https://asia.pokemon-card.com/tw/card-img/tw00002618.png"
      },
      "044/164": {
        "name": "古月鳥",
        "rarity": "—",
        "image": "https://asia.pokemon-card.com/tw/card-img/tw00002619.png"
      },
      "045/164": {
        "name": "古月鳥",
        "rarity": "—",
        "image": "https://asia.pokemon-card.com/tw/card-img/tw00002620.png"
      },
      "046/164": {
        "name": "雪吞蟲",
        "rarity": "—",
        "image": "https://asia.pokemon-card.com/tw/card-img/tw00002621.png"
      },
      "047/164": {
        "name": "雪絨蛾",
        "rarity": "—",
        "image": "https://asia.pokemon-card.com/tw/card-img/tw00002622.png"
      },
      "048/164": {
        "name": "皮卡丘",
        "rarity": "—",
        "image": "https://asia.pokemon-card.com/tw/card-img/tw00002623.png"
      },
      "049/164": {
        "name": "雷丘",
        "rarity": "—",
        "image": "https://asia.pokemon-card.com/tw/card-img/tw00002624.png"
      },
      "050/164": {
        "name": "燈籠魚",
        "rarity": "—",
        "image": "https://asia.pokemon-card.com/tw/card-img/tw00002625.png"
      },
      "051/164": {
        "name": "電燈怪",
        "rarity": "—",
        "image": "https://asia.pokemon-card.com/tw/card-img/tw00002626.png"
      },
      "052/164": {
        "name": "電電蟲",
        "rarity": "—",
        "image": "https://asia.pokemon-card.com/tw/card-img/tw00002627.png"
      },
      "053/164": {
        "name": "電蜘蛛",
        "rarity": "—",
        "image": "https://asia.pokemon-card.com/tw/card-img/tw00002628.png"
      },
      "054/164": {
        "name": "傘電蜥",
        "rarity": "—",
        "image": "https://asia.pokemon-card.com/tw/card-img/tw00002629.png"
      },
      "055/164": {
        "name": "光電傘蜥",
        "rarity": "—",
        "image": "https://asia.pokemon-card.com/tw/card-img/tw00002630.png"
      },
      "056/164": {
        "name": "卡璞・鳴鳴V",
        "rarity": "—",
        "image": "https://asia.pokemon-card.com/tw/card-img/tw00002631.png"
      },
      "057/164": {
        "name": "來電汪",
        "rarity": "—",
        "image": "https://asia.pokemon-card.com/tw/card-img/tw00002632.png"
      },
      "058/164": {
        "name": "逐電犬",
        "rarity": "—",
        "image": "https://asia.pokemon-card.com/tw/card-img/tw00002633.png"
      },
      "059/164": {
        "name": "毒電嬰",
        "rarity": "—",
        "image": "https://asia.pokemon-card.com/tw/card-img/tw00002634.png"
      },
      "060/164": {
        "name": "顫弦蠑螈",
        "rarity": "—",
        "image": "https://asia.pokemon-card.com/tw/card-img/tw00002635.png"
      },
      "061/164": {
        "name": "顫弦蠑螈V",
        "rarity": "—",
        "image": "https://asia.pokemon-card.com/tw/card-img/tw00002636.png"
      },
      "062/164": {
        "name": "啪嚓海膽",
        "rarity": "—",
        "image": "https://asia.pokemon-card.com/tw/card-img/tw00002637.png"
      },
      "063/164": {
        "name": "莫魯貝可",
        "rarity": "—",
        "image": "https://asia.pokemon-card.com/tw/card-img/tw00002638.png"
      },
      "064/164": {
        "name": "莫魯貝可",
        "rarity": "—",
        "image": "https://asia.pokemon-card.com/tw/card-img/tw00002639.png"
      },
      "065/164": {
        "name": "莫魯貝可V",
        "rarity": "—",
        "image": "https://asia.pokemon-card.com/tw/card-img/tw00002640.png"
      },
      "066/164": {
        "name": "伽勒爾 小火馬",
        "rarity": "—",
        "image": "https://asia.pokemon-card.com/tw/card-img/tw00002641.png"
      },
      "067/164": {
        "name": "伽勒爾 烈焰馬",
        "rarity": "—",
        "image": "https://asia.pokemon-card.com/tw/card-img/tw00002642.png"
      },
      "068/164": {
        "name": "天然雀",
        "rarity": "—",
        "image": "https://asia.pokemon-card.com/tw/card-img/tw00002643.png"
      },
      "069/164": {
        "name": "天然鳥",
        "rarity": "—",
        "image": "https://asia.pokemon-card.com/tw/card-img/tw00002644.png"
      },
      "070/164": {
        "name": "食夢夢",
        "rarity": "—",
        "image": "https://asia.pokemon-card.com/tw/card-img/tw00002645.png"
      },
      "071/164": {
        "name": "夢夢蝕",
        "rarity": "—",
        "image": "https://asia.pokemon-card.com/tw/card-img/tw00002646.png"
      },
      "072/164": {
        "name": "象徵鳥",
        "rarity": "—",
        "image": "https://asia.pokemon-card.com/tw/card-img/tw00002647.png"
      },
      "073/164": {
        "name": "小仙奶",
        "rarity": "—",
        "image": "https://asia.pokemon-card.com/tw/card-img/tw00002648.png"
      },
      "074/164": {
        "name": "霜奶仙",
        "rarity": "—",
        "image": "https://asia.pokemon-card.com/tw/card-img/tw00002649.png"
      },
      "075/164": {
        "name": "愛管侍",
        "rarity": "—",
        "image": "https://asia.pokemon-card.com/tw/card-img/tw00002650.png"
      },
      "076/164": {
        "name": "愛管侍V",
        "rarity": "—",
        "image": "https://asia.pokemon-card.com/tw/card-img/tw00002651.png"
      },
      "077/164": {
        "name": "多龍梅西亞",
        "rarity": "—",
        "image": "https://asia.pokemon-card.com/tw/card-img/tw00002652.png"
      },
      "078/164": {
        "name": "多龍奇",
        "rarity": "—",
        "image": "https://asia.pokemon-card.com/tw/card-img/tw00002653.png"
      },
      "079/164": {
        "name": "多龍巴魯托",
        "rarity": "—",
        "image": "https://asia.pokemon-card.com/tw/card-img/tw00002654.png"
      },
      "080/164": {
        "name": "多龍巴魯托V",
        "rarity": "—",
        "image": "https://asia.pokemon-card.com/tw/card-img/tw00002655.png"
      },
      "081/164": {
        "name": "地鼠",
        "rarity": "—",
        "image": "https://asia.pokemon-card.com/tw/card-img/tw00002656.png"
      },
      "082/164": {
        "name": "三地鼠",
        "rarity": "—",
        "image": "https://asia.pokemon-card.com/tw/card-img/tw00002657.png"
      },
      "083/164": {
        "name": "伽勒爾 大蔥鴨",
        "rarity": "—",
        "image": "https://asia.pokemon-card.com/tw/card-img/tw00002658.png"
      },
      "084/164": {
        "name": "伽勒爾 蔥遊兵",
        "rarity": "—",
        "image": "https://asia.pokemon-card.com/tw/card-img/tw00002659.png"
      },
      "085/164": {
        "name": "獨角犀牛",
        "rarity": "—",
        "image": "https://asia.pokemon-card.com/tw/card-img/tw00002660.png"
      },
      "086/164": {
        "name": "鑽角犀獸",
        "rarity": "—",
        "image": "https://asia.pokemon-card.com/tw/card-img/tw00002661.png"
      },
      "087/164": {
        "name": "樹才怪",
        "rarity": "—",
        "image": "https://asia.pokemon-card.com/tw/card-img/tw00002662.png"
      },
      "088/164": {
        "name": "泥泥鰍",
        "rarity": "—",
        "image": "https://asia.pokemon-card.com/tw/card-img/tw00002663.png"
      },
      "089/164": {
        "name": "鯰魚王",
        "rarity": "—",
        "image": "https://asia.pokemon-card.com/tw/card-img/tw00002664.png"
      },
      "090/164": {
        "name": "天秤偶",
        "rarity": "—",
        "image": "https://asia.pokemon-card.com/tw/card-img/tw00002665.png"
      },
      "091/164": {
        "name": "泥驢仔",
        "rarity": "—",
        "image": "https://asia.pokemon-card.com/tw/card-img/tw00002666.png"
      },
      "092/164": {
        "name": "重泥挽馬",
        "rarity": "—",
        "image": "https://asia.pokemon-card.com/tw/card-img/tw00002667.png"
      },
      "093/164": {
        "name": "沙包蛇",
        "rarity": "—",
        "image": "https://asia.pokemon-card.com/tw/card-img/tw00002668.png"
      },
      "094/164": {
        "name": "沙螺蟒",
        "rarity": "—",
        "image": "https://asia.pokemon-card.com/tw/card-img/tw00002669.png"
      },
      "095/164": {
        "name": "沙螺蟒V",
        "rarity": "—",
        "image": "https://asia.pokemon-card.com/tw/card-img/tw00002670.png"
      },
      "096/164": {
        "name": "拳拳蛸",
        "rarity": "—",
        "image": "https://asia.pokemon-card.com/tw/card-img/tw00002671.png"
      },
      "097/164": {
        "name": "巨石丁",
        "rarity": "—",
        "image": "https://asia.pokemon-card.com/tw/card-img/tw00002672.png"
      },
      "098/164": {
        "name": "巨石丁V",
        "rarity": "—",
        "image": "https://asia.pokemon-card.com/tw/card-img/tw00002673.png"
      },
      "099/164": {
        "name": "瓦斯彈",
        "rarity": "—",
        "image": "https://asia.pokemon-card.com/tw/card-img/tw00002674.png"
      },
      "100/164": {
        "name": "伽勒爾 蛇紋熊",
        "rarity": "—",
        "image": "https://asia.pokemon-card.com/tw/card-img/tw00002675.png"
      },
      "101/164": {
        "name": "伽勒爾 直衝熊",
        "rarity": "—",
        "image": "https://asia.pokemon-card.com/tw/card-img/tw00002676.png"
      },
      "102/164": {
        "name": "勾魂眼V",
        "rarity": "—",
        "image": "https://asia.pokemon-card.com/tw/card-img/tw00002677.png"
      },
      "103/164": {
        "name": "臭鼬噗",
        "rarity": "—",
        "image": "https://asia.pokemon-card.com/tw/card-img/tw00002678.png"
      },
      "104/164": {
        "name": "坦克臭鼬",
        "rarity": "—",
        "image": "https://asia.pokemon-card.com/tw/card-img/tw00002679.png"
      },
      "105/164": {
        "name": "鉗尾蠍",
        "rarity": "—",
        "image": "https://asia.pokemon-card.com/tw/card-img/tw00002680.png"
      },
      "106/164": {
        "name": "龍王蠍",
        "rarity": "—",
        "image": "https://asia.pokemon-card.com/tw/card-img/tw00002681.png"
      },
      "107/164": {
        "name": "不良蛙",
        "rarity": "—",
        "image": "https://asia.pokemon-card.com/tw/card-img/tw00002682.png"
      },
      "108/164": {
        "name": "禿鷹丫頭",
        "rarity": "—",
        "image": "https://asia.pokemon-card.com/tw/card-img/tw00002683.png"
      },
      "109/164": {
        "name": "禿鷹娜",
        "rarity": "—",
        "image": "https://asia.pokemon-card.com/tw/card-img/tw00002684.png"
      },
      "110/164": {
        "name": "烏賊王V",
        "rarity": "—",
        "image": "https://asia.pokemon-card.com/tw/card-img/tw00002685.png"
      },
      "111/164": {
        "name": "偷兒狐",
        "rarity": "—",
        "image": "https://asia.pokemon-card.com/tw/card-img/tw00002686.png"
      },
      "112/164": {
        "name": "狐大盜",
        "rarity": "—",
        "image": "https://asia.pokemon-card.com/tw/card-img/tw00002687.png"
      },
      "113/164": {
        "name": "搗蛋小妖",
        "rarity": "—",
        "image": "https://asia.pokemon-card.com/tw/card-img/tw00002688.png"
      },
      "114/164": {
        "name": "詐唬魔",
        "rarity": "—",
        "image": "https://asia.pokemon-card.com/tw/card-img/tw00002689.png"
      },
      "115/164": {
        "name": "長毛巨魔",
        "rarity": "—",
        "image": "https://asia.pokemon-card.com/tw/card-img/tw00002690.png"
      },
      "116/164": {
        "name": "伽勒爾 喵喵",
        "rarity": "—",
        "image": "https://asia.pokemon-card.com/tw/card-img/tw00002691.png"
      },
      "117/164": {
        "name": "伽勒爾 喵頭目",
        "rarity": "—",
        "image": "https://asia.pokemon-card.com/tw/card-img/tw00002692.png"
      },
      "118/164": {
        "name": "巨鉗螳螂",
        "rarity": "—",
        "image": "https://asia.pokemon-card.com/tw/card-img/tw00002693.png"
      },
      "119/164": {
        "name": "大嘴娃",
        "rarity": "—",
        "image": "https://asia.pokemon-card.com/tw/card-img/tw00002694.png"
      },
      "120/164": {
        "name": "銅鏡怪",
        "rarity": "—",
        "image": "https://asia.pokemon-card.com/tw/card-img/tw00002695.png"
      },
      "121/164": {
        "name": "青銅鐘",
        "rarity": "—",
        "image": "https://asia.pokemon-card.com/tw/card-img/tw00002696.png"
      },
      "122/164": {
        "name": "種子鐵球",
        "rarity": "—",
        "image": "https://asia.pokemon-card.com/tw/card-img/tw00002697.png"
      },
      "123/164": {
        "name": "堅果啞鈴",
        "rarity": "—",
        "image": "https://asia.pokemon-card.com/tw/card-img/tw00002698.png"
      },
      "124/164": {
        "name": "伽勒爾 泥巴魚",
        "rarity": "—",
        "image": "https://asia.pokemon-card.com/tw/card-img/tw00002699.png"
      },
      "125/164": {
        "name": "獨劍鞘",
        "rarity": "—",
        "image": "https://asia.pokemon-card.com/tw/card-img/tw00002700.png"
      },
      "126/164": {
        "name": "雙劍鞘",
        "rarity": "—",
        "image": "https://asia.pokemon-card.com/tw/card-img/tw00002701.png"
      },
      "127/164": {
        "name": "堅盾劍怪",
        "rarity": "—",
        "image": "https://asia.pokemon-card.com/tw/card-img/tw00002702.png"
      },
      "128/164": {
        "name": "鋼鎧鴉",
        "rarity": "—",
        "image": "https://asia.pokemon-card.com/tw/card-img/tw00002703.png"
      },
      "129/164": {
        "name": "大王銅象V",
        "rarity": "—",
        "image": "https://asia.pokemon-card.com/tw/card-img/tw00002704.png"
      },
      "130/164": {
        "name": "鋁鋼龍",
        "rarity": "—",
        "image": "https://asia.pokemon-card.com/tw/card-img/tw00002705.png"
      },
      "131/164": {
        "name": "鋁鋼龍",
        "rarity": "—",
        "image": "https://asia.pokemon-card.com/tw/card-img/tw00002706.png"
      },
      "132/164": {
        "name": "卡比獸",
        "rarity": "—",
        "image": "https://asia.pokemon-card.com/tw/card-img/tw00002707.png"
      },
      "133/164": {
        "name": "卡比獸V",
        "rarity": "—",
        "image": "https://asia.pokemon-card.com/tw/card-img/tw00002708.png"
      },
      "134/164": {
        "name": "烈空坐",
        "rarity": "—",
        "image": "https://asia.pokemon-card.com/tw/card-img/tw00002709.png"
      },
      "135/164": {
        "name": "泡沫栗鼠",
        "rarity": "—",
        "image": "https://asia.pokemon-card.com/tw/card-img/tw00002710.png"
      },
      "136/164": {
        "name": "童偶熊",
        "rarity": "—",
        "image": "https://asia.pokemon-card.com/tw/card-img/tw00002711.png"
      },
      "137/164": {
        "name": "穿著熊",
        "rarity": "—",
        "image": "https://asia.pokemon-card.com/tw/card-img/tw00002712.png"
      },
      "138/164": {
        "name": "智揮猩",
        "rarity": "—",
        "image": "https://asia.pokemon-card.com/tw/card-img/tw00002713.png"
      },
      "139/164": {
        "name": "老翁龍",
        "rarity": "—",
        "image": "https://asia.pokemon-card.com/tw/card-img/tw00002714.png"
      },
      "140/164": {
        "name": "稚山雀",
        "rarity": "—",
        "image": "https://asia.pokemon-card.com/tw/card-img/tw00002715.png"
      },
      "141/164": {
        "name": "藍鴉",
        "rarity": "—",
        "image": "https://asia.pokemon-card.com/tw/card-img/tw00002716.png"
      },
      "142/164": {
        "name": "毛辮羊",
        "rarity": "—",
        "image": "https://asia.pokemon-card.com/tw/card-img/tw00002717.png"
      },
      "143/164": {
        "name": "毛毛角羊",
        "rarity": "—",
        "image": "https://asia.pokemon-card.com/tw/card-img/tw00002718.png"
      },
      "144/164": {
        "name": "古月鳥V",
        "rarity": "—",
        "image": "https://asia.pokemon-card.com/tw/card-img/tw00002719.png"
      },
      "145/164": {
        "name": "能量回收",
        "rarity": "—",
        "image": "https://asia.pokemon-card.com/tw/card-img/tw00002720.png"
      },
      "146/164": {
        "name": "能量轉移",
        "rarity": "—",
        "image": "https://asia.pokemon-card.com/tw/card-img/tw00002721.png"
      },
      "147/164": {
        "name": "能量輸送",
        "rarity": "—",
        "image": "https://asia.pokemon-card.com/tw/card-img/tw00002722.png"
      },
      "148/164": {
        "name": "傷藥",
        "rarity": "—",
        "image": "https://asia.pokemon-card.com/tw/card-img/tw00002723.png"
      },
      "149/164": {
        "name": "先機球",
        "rarity": "—",
        "image": "https://asia.pokemon-card.com/tw/card-img/tw00002724.png"
      },
      "150/164": {
        "name": "粉碎之錘",
        "rarity": "—",
        "image": "https://asia.pokemon-card.com/tw/card-img/tw00002725.png"
      },
      "151/164": {
        "name": "超級球",
        "rarity": "—",
        "image": "https://asia.pokemon-card.com/tw/card-img/tw00002726.png"
      },
      "152/164": {
        "name": "萬靈藥",
        "rarity": "—",
        "image": "https://asia.pokemon-card.com/tw/card-img/tw00002727.png"
      },
      "153/164": {
        "name": "神奇糖果",
        "rarity": "—",
        "image": "https://asia.pokemon-card.com/tw/card-img/tw00002728.png"
      },
      "154/164": {
        "name": "普通釣竿",
        "rarity": "—",
        "image": "https://asia.pokemon-card.com/tw/card-img/tw00002729.png"
      },
      "155/164": {
        "name": "寶可夢交替",
        "rarity": "—",
        "image": "https://asia.pokemon-card.com/tw/card-img/tw00002730.png"
      },
      "156/164": {
        "name": "寶可夢捕捉器",
        "rarity": "—",
        "image": "https://asia.pokemon-card.com/tw/card-img/tw00002731.png"
      },
      "157/164": {
        "name": "精靈球",
        "rarity": "—",
        "image": "https://asia.pokemon-card.com/tw/card-img/tw00002732.png"
      },
      "158/164": {
        "name": "博士的研究 木蘭博士",
        "rarity": "—",
        "image": "https://asia.pokemon-card.com/tw/card-img/tw00002733.png"
      },
      "159/164": {
        "name": "寶可夢小朋友",
        "rarity": "—",
        "image": "https://asia.pokemon-card.com/tw/card-img/tw00002734.png"
      },
      "160/164": {
        "name": "寶可夢中心的姐姐",
        "rarity": "—",
        "image": "https://asia.pokemon-card.com/tw/card-img/tw00002735.png"
      },
      "161/164": {
        "name": "老大的指令 坂木",
        "rarity": "—",
        "image": "https://asia.pokemon-card.com/tw/card-img/tw00002736.png"
      },
      "162/164": {
        "name": "赫普",
        "rarity": "—",
        "image": "https://asia.pokemon-card.com/tw/card-img/tw00002737.png"
      },
      "163/164": {
        "name": "瑪俐",
        "rarity": "—",
        "image": "https://asia.pokemon-card.com/tw/card-img/tw00002738.png"
      },
      "164/164": {
        "name": "亞洛",
        "rarity": "—",
        "image": "https://asia.pokemon-card.com/tw/card-img/tw00002739.png"
      }
    },
    "releaseDate": "2020-06-19"
  }
}