{
  "SV11W": {
    "name": "純白閃焰",
    "cards": {
      "001/086": {
        "name": "蟲寶包",
        "rarity": "C",
        "image": "https://asia.pokemon-card.com/tw/card-img/tw00013029.png"
      },
      "002/086": {
        "name": "寶包繭",
        "rarity": "C",
        "image": "https://asia.pokemon-card.com/tw/card-img/tw00013030.png"
      },
      "003/086": {
        "name": "保母蟲",
        "rarity": "U",
        "image": "https://asia.pokemon-card.com/tw/card-img/tw00013031.png"
      },
      "004/086": {
        "name": "木棉球",
        "rarity": "C",
        "image": "https://asia.pokemon-card.com/tw/card-img/tw00013032.png"
      },
      "005/086": {
        "name": "風妖精ex",
        "rarity": "RR",
        "image": "https://asia.pokemon-card.com/tw/card-img/tw00013033.png"
      },
      "006/086": {
        "name": "四季鹿",
        "rarity": "C",
        "image": "https://asia.pokemon-card.com/tw/card-img/tw00013034.png"
      },
      "007/086": {
        "name": "萌芽鹿",
        "rarity": "U",
        "image": "https://asia.pokemon-card.com/tw/card-img/tw00013035.png"
      },
      "008/086": {
        "name": "小嘴蝸",
        "rarity": "C",
        "image": "https://asia.pokemon-card.com/tw/card-img/tw00013036.png"
      },
      "009/086": {
        "name": "敏捷蟲",
        "rarity": "U",
        "image": "https://asia.pokemon-card.com/tw/card-img/tw00013037.png"
      },
      "010/086": {
        "name": "畢力吉翁",
        "rarity": "R",
        "image": "https://asia.pokemon-card.com/tw/card-img/tw00013038.png"
      },
      "011/086": {
        "name": "暖暖豬",
        "rarity": "C",
        "image": "https://asia.pokemon-card.com/tw/card-img/tw00013039.png"
      },
      "012/086": {
        "name": "炒炒豬",
        "rarity": "C",
        "image": "https://asia.pokemon-card.com/tw/card-img/tw00013040.png"
      },
      "013/086": {
        "name": "炎武王",
        "rarity": "R",
        "image": "https://asia.pokemon-card.com/tw/card-img/tw00013041.png"
      },
      "014/086": {
        "name": "爆香猴",
        "rarity": "C",
        "image": "https://asia.pokemon-card.com/tw/card-img/tw00013042.png"
      },
      "015/086": {
        "name": "爆香猿",
        "rarity": "U",
        "image": "https://asia.pokemon-card.com/tw/card-img/tw00013043.png"
      },
      "016/086": {
        "name": "熔蟻獸",
        "rarity": "U",
        "image": "https://asia.pokemon-card.com/tw/card-img/tw00013044.png"
      },
      "017/086": {
        "name": "萊希拉姆ex",
        "rarity": "RR",
        "image": "https://asia.pokemon-card.com/tw/card-img/tw00013045.png"
      },
      "018/086": {
        "name": "水水獺",
        "rarity": "C",
        "image": "https://asia.pokemon-card.com/tw/card-img/tw00013046.png"
      },
      "019/086": {
        "name": "雙刃丸",
        "rarity": "C",
        "image": "https://asia.pokemon-card.com/tw/card-img/tw00013047.png"
      },
      "020/086": {
        "name": "大劍鬼",
        "rarity": "R",
        "image": "https://asia.pokemon-card.com/tw/card-img/tw00013048.png"
      },
      "021/086": {
        "name": "野蠻鱸魚",
        "rarity": "C",
        "image": "https://asia.pokemon-card.com/tw/card-img/tw00013049.png"
      },
      "022/086": {
        "name": "鴨寶寶",
        "rarity": "C",
        "image": "https://asia.pokemon-card.com/tw/card-img/tw00013050.png"
      },
      "023/086": {
        "name": "舞天鵝",
        "rarity": "U",
        "image": "https://asia.pokemon-card.com/tw/card-img/tw00013051.png"
      },
      "024/086": {
        "name": "迷你冰",
        "rarity": "C",
        "image": "https://asia.pokemon-card.com/tw/card-img/tw00013052.png"
      },
      "025/086": {
        "name": "多多冰",
        "rarity": "C",
        "image": "https://asia.pokemon-card.com/tw/card-img/tw00013053.png"
      },
      "026/086": {
        "name": "雙倍多多冰",
        "rarity": "U",
        "image": "https://asia.pokemon-card.com/tw/card-img/tw00013054.png"
      },
      "027/086": {
        "name": "凱路迪歐ex",
        "rarity": "RR",
        "image": "https://asia.pokemon-card.com/tw/card-img/tw00013055.png"
      },
      "028/086": {
        "name": "斑斑馬",
        "rarity": "C",
        "image": "https://asia.pokemon-card.com/tw/card-img/tw00013056.png"
      },
      "029/086": {
        "name": "雷電斑馬",
        "rarity": "U",
        "image": "https://asia.pokemon-card.com/tw/card-img/tw00013057.png"
      },
      "030/086": {
        "name": "電電蟲",
        "rarity": "C",
        "image": "https://asia.pokemon-card.com/tw/card-img/tw00013058.png"
      },
      "031/086": {
        "name": "電蜘蛛",
        "rarity": "U",
        "image": "https://asia.pokemon-card.com/tw/card-img/tw00013059.png"
      },
      "032/086": {
        "name": "泥巴魚",
        "rarity": "U",
        "image": "https://asia.pokemon-card.com/tw/card-img/tw00013060.png"
      },
      "033/086": {
        "name": "滾滾蝙蝠",
        "rarity": "C",
        "image": "https://asia.pokemon-card.com/tw/card-img/tw00013061.png"
      },
      "034/086": {
        "name": "心蝙蝠",
        "rarity": "U",
        "image": "https://asia.pokemon-card.com/tw/card-img/tw00013062.png"
      },
      "035/086": {
        "name": "象徵鳥",
        "rarity": "U",
        "image": "https://asia.pokemon-card.com/tw/card-img/tw00013063.png"
      },
      "036/086": {
        "name": "哭哭面具",
        "rarity": "C",
        "image": "https://asia.pokemon-card.com/tw/card-img/tw00013064.png"
      },
      "037/086": {
        "name": "死神棺",
        "rarity": "R",
        "image": "https://asia.pokemon-card.com/tw/card-img/tw00013065.png"
      },
      "038/086": {
        "name": "哥德寶寶",
        "rarity": "C",
        "image": "https://asia.pokemon-card.com/tw/card-img/tw00013066.png"
      },
      "039/086": {
        "name": "哥德小童",
        "rarity": "C",
        "image": "https://asia.pokemon-card.com/tw/card-img/tw00013067.png"
      },
      "040/086": {
        "name": "哥德小姐",
        "rarity": "R",
        "image": "https://asia.pokemon-card.com/tw/card-img/tw00013068.png"
      },
      "041/086": {
        "name": "輕飄飄",
        "rarity": "C",
        "image": "https://asia.pokemon-card.com/tw/card-img/tw00013069.png"
      },
      "042/086": {
        "name": "胖嘟嘟ex",
        "rarity": "RR",
        "image": "https://asia.pokemon-card.com/tw/card-img/tw00013070.png"
      },
      "043/086": {
        "name": "石丸子",
        "rarity": "C",
        "image": "https://asia.pokemon-card.com/tw/card-img/tw00013071.png"
      },
      "044/086": {
        "name": "地幔岩",
        "rarity": "C",
        "image": "https://asia.pokemon-card.com/tw/card-img/tw00013072.png"
      },
      "045/086": {
        "name": "龐岩怪",
        "rarity": "U",
        "image": "https://asia.pokemon-card.com/tw/card-img/tw00013073.png"
      },
      "046/086": {
        "name": "打擊鬼",
        "rarity": "U",
        "image": "https://asia.pokemon-card.com/tw/card-img/tw00013074.png"
      },
      "047/086": {
        "name": "始祖小鳥",
        "rarity": "U",
        "image": "https://asia.pokemon-card.com/tw/card-img/tw00013075.png"
      },
      "048/086": {
        "name": "始祖大鳥",
        "rarity": "R",
        "image": "https://asia.pokemon-card.com/tw/card-img/tw00013076.png"
      },
      "049/086": {
        "name": "功夫鼬",
        "rarity": "C",
        "image": "https://asia.pokemon-card.com/tw/card-img/tw00013077.png"
      },
      "050/086": {
        "name": "師父鼬",
        "rarity": "U",
        "image": "https://asia.pokemon-card.com/tw/card-img/tw00013078.png"
      },
      "051/086": {
        "name": "代拉基翁",
        "rarity": "R",
        "image": "https://asia.pokemon-card.com/tw/card-img/tw00013079.png"
      },
      "052/086": {
        "name": "扒手貓",
        "rarity": "C",
        "image": "https://asia.pokemon-card.com/tw/card-img/tw00013080.png"
      },
      "053/086": {
        "name": "酷豹",
        "rarity": "U",
        "image": "https://asia.pokemon-card.com/tw/card-img/tw00013081.png"
      },
      "054/086": {
        "name": "滑滑小子",
        "rarity": "C",
        "image": "https://asia.pokemon-card.com/tw/card-img/tw00013082.png"
      },
      "055/086": {
        "name": "頭巾混混",
        "rarity": "U",
        "image": "https://asia.pokemon-card.com/tw/card-img/tw00013083.png"
      },
      "056/086": {
        "name": "破破袋",
        "rarity": "C",
        "image": "https://asia.pokemon-card.com/tw/card-img/tw00013084.png"
      },
      "057/086": {
        "name": "灰塵山",
        "rarity": "U",
        "image": "https://asia.pokemon-card.com/tw/card-img/tw00013085.png"
      },
      "058/086": {
        "name": "索羅亞",
        "rarity": "C",
        "image": "https://asia.pokemon-card.com/tw/card-img/tw00013086.png"
      },
      "059/086": {
        "name": "索羅亞克",
        "rarity": "R",
        "image": "https://asia.pokemon-card.com/tw/card-img/tw00013087.png"
      },
      "060/086": {
        "name": "單首龍",
        "rarity": "C",
        "image": "https://asia.pokemon-card.com/tw/card-img/tw00013088.png"
      },
      "061/086": {
        "name": "雙首暴龍",
        "rarity": "C",
        "image": "https://asia.pokemon-card.com/tw/card-img/tw00013089.png"
      },
      "062/086": {
        "name": "三首惡龍ex",
        "rarity": "RR",
        "image": "https://asia.pokemon-card.com/tw/card-img/tw00013090.png"
      },
      "063/086": {
        "name": "種子鐵球",
        "rarity": "C",
        "image": "https://asia.pokemon-card.com/tw/card-img/tw00013091.png"
      },
      "064/086": {
        "name": "堅果啞鈴",
        "rarity": "U",
        "image": "https://asia.pokemon-card.com/tw/card-img/tw00013092.png"
      },
      "065/086": {
        "name": "齒輪兒",
        "rarity": "C",
        "image": "https://asia.pokemon-card.com/tw/card-img/tw00013093.png"
      },
      "066/086": {
        "name": "齒輪組",
        "rarity": "C",
        "image": "https://asia.pokemon-card.com/tw/card-img/tw00013094.png"
      },
      "067/086": {
        "name": "齒輪怪",
        "rarity": "R",
        "image": "https://asia.pokemon-card.com/tw/card-img/tw00013095.png"
      },
      "068/086": {
        "name": "鐵蟻",
        "rarity": "U",
        "image": "https://asia.pokemon-card.com/tw/card-img/tw00013096.png"
      },
      "069/086": {
        "name": "赤面龍",
        "rarity": "U",
        "image": "https://asia.pokemon-card.com/tw/card-img/tw00013097.png"
      },
      "070/086": {
        "name": "探探鼠",
        "rarity": "C",
        "image": "https://asia.pokemon-card.com/tw/card-img/tw00013098.png"
      },
      "071/086": {
        "name": "步哨鼠",
        "rarity": "U",
        "image": "https://asia.pokemon-card.com/tw/card-img/tw00013099.png"
      },
      "072/086": {
        "name": "小約克",
        "rarity": "C",
        "image": "https://asia.pokemon-card.com/tw/card-img/tw00013100.png"
      },
      "073/086": {
        "name": "哈約克",
        "rarity": "C",
        "image": "https://asia.pokemon-card.com/tw/card-img/tw00013101.png"
      },
      "074/086": {
        "name": "長毛狗",
        "rarity": "U",
        "image": "https://asia.pokemon-card.com/tw/card-img/tw00013102.png"
      },
      "075/086": {
        "name": "爆炸頭水牛ex",
        "rarity": "RR",
        "image": "https://asia.pokemon-card.com/tw/card-img/tw00013103.png"
      },
      "076/086": {
        "name": "毛頭小鷹",
        "rarity": "C",
        "image": "https://asia.pokemon-card.com/tw/card-img/tw00013104.png"
      },
      "077/086": {
        "name": "勇士雄鷹",
        "rarity": "U",
        "image": "https://asia.pokemon-card.com/tw/card-img/tw00013105.png"
      },
      "078/086": {
        "name": "龍捲雲",
        "rarity": "R",
        "image": "https://asia.pokemon-card.com/tw/card-img/tw00013106.png"
      },
      "079/086": {
        "name": "能量回收",
        "rarity": "U",
        "image": "https://asia.pokemon-card.com/tw/card-img/tw00013107.png"
      },
      "080/086": {
        "name": "道具拆除器",
        "rarity": "U",
        "image": "https://asia.pokemon-card.com/tw/card-img/tw00013108.png"
      },
      "081/086": {
        "name": "陳舊的根狀化石",
        "rarity": "C",
        "image": "https://asia.pokemon-card.com/tw/card-img/tw00013109.png"
      },
      "082/086": {
        "name": "猛攻手鐲",
        "rarity": "U",
        "image": "https://asia.pokemon-card.com/tw/card-img/tw00013110.png"
      },
      "083/086": {
        "name": "滑稽演員",
        "rarity": "U",
        "image": "https://asia.pokemon-card.com/tw/card-img/tw00013111.png"
      },
      "084/086": {
        "name": "黑連",
        "rarity": "U",
        "image": "https://asia.pokemon-card.com/tw/card-img/tw00013112.png"
      },
      "085/086": {
        "name": "鬥子",
        "rarity": "U",
        "image": "https://asia.pokemon-card.com/tw/card-img/tw00013113.png"
      },
      "086/086": {
        "name": "燃火能量",
        "rarity": "U",
        "image": "https://asia.pokemon-card.com/tw/card-img/tw00013114.png"
      },
      "087/086": {
        "name": "蟲寶包",
        "rarity": "AR",
        "image": ""
      },
      "088/086": {
        "name": "寶包繭",
        "rarity": "AR",
        "image": ""
      },
      "089/086": {
        "name": "保母蟲",
        "rarity": "AR",
        "image": ""
      },
      "090/086": {
        "name": "木棉球",
        "rarity": "AR",
        "image": ""
      },
      "091/086": {
        "name": "四季鹿",
        "rarity": "AR",
        "image": ""
      },
      "092/086": {
        "name": "萌芽鹿",
        "rarity": "AR",
        "image": ""
      },
      "093/086": {
        "name": "小嘴蝸",
        "rarity": "AR",
        "image": ""
      },
      "094/086": {
        "name": "敏捷蟲",
        "rarity": "AR",
        "image": ""
      },
      "095/086": {
        "name": "畢力吉翁",
        "rarity": "AR",
        "image": ""
      },
      "096/086": {
        "name": "暖暖豬",
        "rarity": "AR",
        "image": ""
      },
      "097/086": {
        "name": "炒炒豬",
        "rarity": "AR",
        "image": ""
      },
      "098/086": {
        "name": "炎武王",
        "rarity": "AR",
        "image": ""
      },
      "099/086": {
        "name": "爆香猴",
        "rarity": "AR",
        "image": ""
      },
      "100/086": {
        "name": "爆香猿",
        "rarity": "AR",
        "image": ""
      },
      "101/086": {
        "name": "熔蟻獸",
        "rarity": "AR",
        "image": ""
      },
      "102/086": {
        "name": "水水獺",
        "rarity": "AR",
        "image": ""
      },
      "103/086": {
        "name": "雙刃丸",
        "rarity": "AR",
        "image": ""
      },
      "104/086": {
        "name": "大劍鬼",
        "rarity": "AR",
        "image": ""
      },
      "105/086": {
        "name": "野蠻鱸魚",
        "rarity": "AR",
        "image": ""
      },
      "106/086": {
        "name": "鴨寶寶",
        "rarity": "AR",
        "image": ""
      },
      "107/086": {
        "name": "舞天鵝",
        "rarity": "AR",
        "image": ""
      },
      "108/086": {
        "name": "迷你冰",
        "rarity": "AR",
        "image": ""
      },
      "109/086": {
        "name": "多多冰",
        "rarity": "AR",
        "image": ""
      },
      "110/086": {
        "name": "雙倍多多冰",
        "rarity": "AR",
        "image": ""
      },
      "111/086": {
        "name": "斑斑馬",
        "rarity": "AR",
        "image": ""
      },
      "112/086": {
        "name": "雷電斑馬",
        "rarity": "AR",
        "image": ""
      },
      "113/086": {
        "name": "電電蟲",
        "rarity": "AR",
        "image": ""
      },
      "114/086": {
        "name": "電蜘蛛",
        "rarity": "AR",
        "image": ""
      },
      "115/086": {
        "name": "泥巴魚",
        "rarity": "AR",
        "image": ""
      },
      "116/086": {
        "name": "滾滾蝙蝠",
        "rarity": "AR",
        "image": ""
      },
      "117/086": {
        "name": "心蝙蝠",
        "rarity": "AR",
        "image": ""
      },
      "118/086": {
        "name": "象徵鳥",
        "rarity": "AR",
        "image": ""
      },
      "119/086": {
        "name": "哭哭面具",
        "rarity": "AR",
        "image": ""
      },
      "120/086": {
        "name": "死神棺",
        "rarity": "AR",
        "image": ""
      },
      "121/086": {
        "name": "哥德寶寶",
        "rarity": "AR",
        "image": ""
      },
      "122/086": {
        "name": "哥德小童",
        "rarity": "AR",
        "image": ""
      },
      "123/086": {
        "name": "哥德小姐",
        "rarity": "AR",
        "image": ""
      },
      "124/086": {
        "name": "輕飄飄",
        "rarity": "AR",
        "image": ""
      },
      "125/086": {
        "name": "石丸子",
        "rarity": "AR",
        "image": ""
      },
      "126/086": {
        "name": "地幔岩",
        "rarity": "AR",
        "image": ""
      },
      "127/086": {
        "name": "龐岩怪",
        "rarity": "AR",
        "image": ""
      },
      "128/086": {
        "name": "打擊鬼",
        "rarity": "AR",
        "image": ""
      },
      "129/086": {
        "name": "始祖小鳥",
        "rarity": "AR",
        "image": ""
      },
      "130/086": {
        "name": "始祖大鳥",
        "rarity": "AR",
        "image": ""
      },
      "131/086": {
        "name": "功夫鼬",
        "rarity": "AR",
        "image": ""
      },
      "132/086": {
        "name": "師父鼬",
        "rarity": "AR",
        "image": ""
      },
      "133/086": {
        "name": "代拉基翁",
        "rarity": "AR",
        "image": ""
      },
      "134/086": {
        "name": "扒手貓",
        "rarity": "AR",
        "image": ""
      },
      "135/086": {
        "name": "酷豹",
        "rarity": "AR",
        "image": ""
      },
      "136/086": {
        "name": "滑滑小子",
        "rarity": "AR",
        "image": ""
      },
      "137/086": {
        "name": "頭巾混混",
        "rarity": "AR",
        "image": ""
      },
      "138/086": {
        "name": "破破袋",
        "rarity": "AR",
        "image": ""
      },
      "139/086": {
        "name": "灰塵山",
        "rarity": "AR",
        "image": ""
      },
      "140/086": {
        "name": "索羅亞",
        "rarity": "AR",
        "image": ""
      },
      "141/086": {
        "name": "索羅亞克",
        "rarity": "AR",
        "image": ""
      },
      "142/086": {
        "name": "單首龍",
        "rarity": "AR",
        "image": ""
      },
      "143/086": {
        "name": "雙首暴龍",
        "rarity": "AR",
        "image": ""
      },
      "144/086": {
        "name": "種子鐵球",
        "rarity": "AR",
        "image": ""
      },
      "145/086": {
        "name": "堅果啞鈴",
        "rarity": "AR",
        "image": ""
      },
      "146/086": {
        "name": "齒輪兒",
        "rarity": "AR",
        "image": ""
      },
      "147/086": {
        "name": "齒輪組",
        "rarity": "AR",
        "image": ""
      },
      "148/086": {
        "name": "齒輪怪",
        "rarity": "AR",
        "image": ""
      },
      "149/086": {
        "name": "鐵蟻",
        "rarity": "AR",
        "image": ""
      },
      "150/086": {
        "name": "赤面龍",
        "rarity": "AR",
        "image": ""
      },
      "151/086": {
        "name": "探探鼠",
        "rarity": "AR",
        "image": ""
      },
      "152/086": {
        "name": "步哨鼠",
        "rarity": "AR",
        "image": ""
      },
      "153/086": {
        "name": "小約克",
        "rarity": "AR",
        "image": ""
      },
      "154/086": {
        "name": "哈約克",
        "rarity": "AR",
        "image": ""
      },
      "155/086": {
        "name": "長毛狗",
        "rarity": "AR",
        "image": ""
      },
      "156/086": {
        "name": "毛頭小鷹",
        "rarity": "AR",
        "image": ""
      },
      "157/086": {
        "name": "勇士雄鷹",
        "rarity": "AR",
        "image": ""
      },
      "158/086": {
        "name": "龍捲雲",
        "rarity": "AR",
        "image": ""
      },
      "159/086": {
        "name": "風妖精ex",
        "rarity": "SR",
        "image": ""
      },
      "160/086": {
        "name": "萊希拉姆ex",
        "rarity": "SR",
        "image": ""
      },
      "161/086": {
        "name": "凱路迪歐ex",
        "rarity": "SR",
        "image": ""
      },
      "162/086": {
        "name": "胖嘟嘟ex",
        "rarity": "SR",
        "image": ""
      },
      "163/086": {
        "name": "三首惡龍ex",
        "rarity": "SR",
        "image": ""
      },
      "164/086": {
        "name": "爆炸頭水牛ex",
        "rarity": "SR",
        "image": ""
      },
      "165/086": {
        "name": "滑稽演員",
        "rarity": "SR",
        "image": ""
      },
      "166/086": {
        "name": "鬥子",
        "rarity": "SR",
        "image": ""
      },
      "167/086": {
        "name": "風妖精ex",
        "rarity": "SAR",
        "image": ""
      },
      "168/086": {
        "name": "萊希拉姆ex",
        "rarity": "SAR",
        "image": ""
      },
      "169/086": {
        "name": "凱路迪歐ex",
        "rarity": "SAR",
        "image": ""
      },
      "170/086": {
        "name": "胖嘟嘟ex",
        "rarity": "SAR",
        "image": ""
      },
      "171/086": {
        "name": "三首惡龍ex",
        "rarity": "SAR",
        "image": ""
      },
      "172/086": {
        "name": "爆炸頭水牛ex",
        "rarity": "SAR",
        "image": ""
      },
      "173/086": {
        "name": "鬥子",
        "rarity": "SAR",
        "image": ""
      },
      "174/086": {
        "name": "萊希拉姆ex",
        "rarity": "BWR",
        "image": ""
      }
    },
    "releaseDate": "2025-06-20"
  }
}